toolblocks/__init__.py
toolblocks/alerts.py
toolblocks/findings.py
toolblocks/indexing/__init__.py
toolblocks/indexing/parquet.py
toolblocks/indexing/pickle.py
toolblocks/logging.py
toolblocks/parsing/__init__.py
toolblocks/parsing/address.py
toolblocks/parsing/common.py
toolblocks/parsing/env.py
toolblocks/parsing/logs.py
toolblocks/parsing/traces.py
toolblocks/parsing/transaction.py
toolblocks/preprocessing.py
toolblocks/profiling.py
toolblocks/scraping/__init__.py
toolblocks-0.5.0.dist-info/METADATA
toolblocks-0.5.0.dist-info/WHEEL
toolblocks-0.5.0.dist-info/RECORD
