Metadata-Version: 2.1
Name: toolblocks
Version: 0.5.0
Summary: Tools to help with the common problems of blockchain bot development
Author: apehex
Author-email: apehex@protonmail.com
Requires-Python: >=3.8,<4
Classifier: Programming Language :: Python :: 3
Classifier: Programming Language :: Python :: 3.8
Classifier: Programming Language :: Python :: 3.9
Classifier: Programming Language :: Python :: 3.10
Classifier: Programming Language :: Python :: 3.11
Requires-Dist: eth-utils (>=1.9)
Requires-Dist: pyarrow (>=12)
